primeway/__init__.py
primeway/constants.py
primeway/utils.py
primeway/cli/__init__.py
primeway/cli/entry.py
primeway/cli/commands/__init__.py
primeway/cli/commands/create_job.py
primeway/cli/commands/get_logs.py
primeway/cli/commands/manage_jobs.py
primeway/cli/commands/run_job.py
primeway/cli/commands/stop_job.py
primeway-0.1.5.dist-info/METADATA
primeway-0.1.5.dist-info/WHEEL
primeway-0.1.5.dist-info/entry_points.txt
primeway-0.1.5.dist-info/top_level.txt
primeway-0.1.5.dist-info/RECORD
