Metadata-Version: 2.4
Name: primeway
Version: 0.1.5
Summary: Cli for primeway.io
Author: Nikita Lavrenov
Author-email: keith.la.00@gmail.com
License: MIT
Keywords: primeway,mlops
Classifier: Programming Language :: Python :: 3
Classifier: License :: OSI Approved :: MIT License
Classifier: Operating System :: OS Independent
Requires-Python: >=3.10
Requires-Dist: click
Requires-Dist: pyyaml
Requires-Dist: requests
Requires-Dist: tabulate
Requires-Dist: sseclient-py
Requires-Dist: python-dotenv
Dynamic: author
Dynamic: author-email
Dynamic: classifier
Dynamic: description
Dynamic: keywords
Dynamic: license
Dynamic: requires-dist
Dynamic: requires-python
Dynamic: summary
